{
    "Map":{
        "sizeCarrousel":20,
        "xStart":0,
        "yStart":0,
        "nbRow":11,
        "nbColumn":11,
        "layers":[
            [{"tile":2,"rotation":0},{"tile":0,"rotation":0},{"tile":2,"rotation":0},{"tile":2,"rotation":0},{"tile":2,"rotation":0},{"tile":2,"rotation":0},{"tile":2,"rotation":0},{"tile":2,"rotation":0}],
            [{"tile":2,"rotation":0},{"tile":2,"rotation":0},{"tile":2,"rotation":0},{"tile":2,"rotation":0},{"tile":2,"rotation":0},{"tile":2,"rotation":0},{"tile":2,"rotation":0},{"tile":2,"rotation":0}],
            [{"tile":2,"rotation":0},{"tile":1,"rotation":0},{"tile":1,"rotation":0},{"tile":1,"rotation":0},{"tile":1,"rotation":0},{"tile":1,"rotation":0},{"tile":1,"rotation":0},{"tile":2,"rotation":0}],
            [{"tile":2,"rotation":0},{"tile":2,"rotation":0},{"tile":2,"rotation":0},{"tile":2,"rotation":0},{"tile":2,"rotation":0},{"tile":2,"rotation":0},{"tile":2,"rotation":0},{"tile":2,"rotation":0}],
            [{"tile":2,"rotation":0},{"tile":2,"rotation":0},{"tile":2,"rotation":0},{"tile":2,"rotation":0},{"tile":2,"rotation":0},{"tile":2,"rotation":0},{"tile":2,"rotation":0},{"tile":2,"rotation":0}],
            [{"tile":2,"rotation":0},{"tile":3,"rotation":0},{"tile":3,"rotation":0},{"tile":3,"rotation":0},{"tile":3,"rotation":0},{"tile":3,"rotation":0},{"tile":3,"rotation":0},{"tile":2,"rotation":0}],
            [{"tile":2,"rotation":0},{"tile":2,"rotation":0},{"tile":2,"rotation":0},{"tile":2,"rotation":0},{"tile":2,"rotation":0},{"tile":2,"rotation":0},{"tile":2,"rotation":0},{"tile":2,"rotation":0}],
            [{"tile":2,"rotation":0},{"tile":2,"rotation":0},{"tile":2,"rotation":0},{"tile":2,"rotation":0},{"tile":2,"rotation":0},{"tile":2,"rotation":0},{"tile":4,"rotation":0},{"tile":2,"rotation":0}]
        ]
        
    }
}